easy_aws_login/__init__.py
easy_aws_login/index.py
easy_aws_login-0.4.dist-info/LICENCE.txt
easy_aws_login-0.4.dist-info/METADATA
easy_aws_login-0.4.dist-info/WHEEL
easy_aws_login-0.4.dist-info/entry_points.txt
easy_aws_login-0.4.dist-info/top_level.txt
easy_aws_login-0.4.dist-info/RECORD
