Metadata-Version: 2.1
Name: easy-aws-login
Version: 0.4
Summary: The easiest way to log in to your AWS console.
Home-page: https://github.com/jeshan/easy-aws-login
Author: Jeshan Babooa
Author-email: j@jeshan.co
License: BSD-2-Clause
Platform: UNKNOWN
Classifier: License :: OSI Approved :: BSD License
Classifier: Programming Language :: Python
Classifier: Programming Language :: Python :: 3
Classifier: Programming Language :: Python :: 3.6
Requires-Python: >=3.6.0
Requires-Dist: boto3
Requires-Dist: requests
Provides-Extra: boto3_code_assistance
Requires-Dist: botostubs ; extra == 'boto3_code_assistance'
